nba_analytics/__init__.py
nba_analytics/analytics/__init__.py
nba_analytics/analytics/analytics.py
nba_analytics/analytics/graphs.py
nba_analytics/cloud/__init__.py
nba_analytics/cloud/azure/__init__.py
nba_analytics/cloud/azure/bronze_to_silver.py
nba_analytics/cloud/azure/silver_to_gold.py
nba_analytics/cloud/azure/sql_sync.py
nba_analytics/cloud/fabric/__init__.py
nba_analytics/cloud/fabric/data_sync.py
nba_analytics/cloud/fabric/model_sync.py
nba_analytics/cloud/sql/__init__.py
nba_analytics/config/azure.toml
nba_analytics/config/settings.toml
nba_analytics/data/__init__.py
nba_analytics/data/dataset/__init__.py
nba_analytics/data/dataset/torch.py
nba_analytics/data/dataset/torch_overlap.py
nba_analytics/data/io/__init__.py
nba_analytics/data/io/creation.py
nba_analytics/data/io/sql.py
nba_analytics/data/medallion/__init__.py
nba_analytics/data/medallion/bronze_to_silver.py
nba_analytics/data/medallion/silver_to_gold.py
nba_analytics/data/transformation/__init__.py
nba_analytics/data/transformation/cleaning.py
nba_analytics/data/transformation/filtering.py
nba_analytics/data/transformation/processing.py
nba_analytics/data/transformation/reduction.py
nba_analytics/machine_learning/__init__.py
nba_analytics/machine_learning/train_models.py
nba_analytics/machine_learning/use_models.py
nba_analytics/machine_learning/models/__init__.py
nba_analytics/machine_learning/models/arima.py
nba_analytics/machine_learning/models/lstm.py
nba_analytics/machine_learning/models/neuralnet.py
nba_analytics/machine_learning/models/xgboost.py
nba_analytics/utils/__init__.py
nba_analytics/utils/config.py
nba_analytics/utils/filename_grabber.py
nba_analytics/utils/logger.py
nba_analytics/utils/reporting.py
nba_analytics-0.2.19.dist-info/LICENSE
nba_analytics-0.2.19.dist-info/METADATA
nba_analytics-0.2.19.dist-info/WHEEL
nba_analytics-0.2.19.dist-info/top_level.txt
nba_analytics-0.2.19.dist-info/RECORD
