Metadata-Version: 2.1
Name: nba_analytics
Version: 0.2.19
Summary: A package for collecting and analyzing NBA player data.
Home-page: https://github.com/ahernandezjr/nba_analytics
Author: Alexander Hernandez
Author-email: ahernandezjr0@gmail.com
Classifier: Programming Language :: Python :: 3
Classifier: License :: OSI Approved :: MIT License
Classifier: Operating System :: OS Independent
Requires-Python: >=3.10
License-File: LICENSE
Requires-Dist: aiohttp
Requires-Dist: aiosignal
Requires-Dist: asttokens
Requires-Dist: async-timeout
Requires-Dist: attrs
Requires-Dist: azure-core
Requires-Dist: azure-storage-blob
Requires-Dist: azure-storage-file-datalake
Requires-Dist: backcall
Requires-Dist: basketball-reference-web-scraper
Requires-Dist: beautifulsoup4
Requires-Dist: bleach
Requires-Dist: certifi
Requires-Dist: cffi
Requires-Dist: chardet
Requires-Dist: charset-normalizer
Requires-Dist: colorama
Requires-Dist: colorlog
Requires-Dist: comm
Requires-Dist: contourpy
Requires-Dist: cryptography
Requires-Dist: cssutils
Requires-Dist: cycler
Requires-Dist: dataframe-image
Requires-Dist: debugpy
Requires-Dist: decorator
Requires-Dist: defusedxml
Requires-Dist: docopt
Requires-Dist: dynaconf
Requires-Dist: exceptiongroup
Requires-Dist: executing
Requires-Dist: fastjsonschema
Requires-Dist: filelock
Requires-Dist: fonttools
Requires-Dist: fpdf
Requires-Dist: frozenlist
Requires-Dist: fsspec
Requires-Dist: gitdb
Requires-Dist: GitPython
Requires-Dist: html2image
Requires-Dist: idna
Requires-Dist: intel-openmp
Requires-Dist: ipykernel
Requires-Dist: ipython
Requires-Dist: isodate
Requires-Dist: jedi
Requires-Dist: Jinja2
Requires-Dist: joblib
Requires-Dist: jsonschema
Requires-Dist: jsonschema-specifications
Requires-Dist: jupyter-client
Requires-Dist: jupyter-core
Requires-Dist: jupyterlab-pygments
Requires-Dist: kaleido
Requires-Dist: kiwisolver
Requires-Dist: lxml
Requires-Dist: MarkupSafe
Requires-Dist: matplotlib
Requires-Dist: matplotlib-inline
Requires-Dist: mistune
Requires-Dist: mkl
Requires-Dist: more-itertools
Requires-Dist: mpmath
Requires-Dist: multidict
Requires-Dist: nbclient
Requires-Dist: nbconvert
Requires-Dist: nbformat
Requires-Dist: nest-asyncio
Requires-Dist: networkx
Requires-Dist: numpy
Requires-Dist: packaging
Requires-Dist: pandas
Requires-Dist: pandocfilters
Requires-Dist: parso
Requires-Dist: pickleshare
Requires-Dist: pillow
Requires-Dist: pipreqs
Requires-Dist: platformdirs
Requires-Dist: prompt-toolkit
Requires-Dist: psutil
Requires-Dist: pure-eval
Requires-Dist: pycparser
Requires-Dist: Pygments
Requires-Dist: pyparsing
Requires-Dist: python-dateutil
Requires-Dist: pytz
Requires-Dist: pyzmq
Requires-Dist: referencing
Requires-Dist: reportlab
Requires-Dist: requests
Requires-Dist: rpds-py
Requires-Dist: scikit-learn
Requires-Dist: scipy
Requires-Dist: six
Requires-Dist: smmap
Requires-Dist: soupsieve
Requires-Dist: stack-data
Requires-Dist: sympy
Requires-Dist: tbb
Requires-Dist: threadpoolctl
Requires-Dist: tinycss2
Requires-Dist: tornado
Requires-Dist: tqdm
Requires-Dist: traitlets
Requires-Dist: typing-extensions
Requires-Dist: tzdata
Requires-Dist: urllib3
Requires-Dist: wcwidth
Requires-Dist: webencodings
Requires-Dist: websocket-client
Requires-Dist: yarg
Requires-Dist: yarl
